Metadata-Version: 2.1
Name: Topsis-Ira-102017029
Version: 0.2
Summary: TOPSIS Package
Home-page: https://github.com/ira20022/Topsis-Ira-102017029
Author: Ira Vashisht
Author-email: iravashisht2002@gmail.com
License: MIT
Download-URL: https://github.com/ira20022/Topsis-Ira-102017029/archive/refs/tags/0.1.tar.gz
Keywords: TOPSIS,MCDM,102017029
Platform: UNKNOWN
Classifier: Development Status :: 3 - Alpha
Classifier: Intended Audience :: Developers
Classifier: Topic :: Software Development :: Build Tools
Classifier: License :: OSI Approved :: MIT License
Classifier: Programming Language :: Python :: 3
Classifier: Programming Language :: Python :: 3.4
Classifier: Programming Language :: Python :: 3.5
Classifier: Programming Language :: Python :: 3.6
Classifier: Programming Language :: Python :: 3.7
Classifier: Programming Language :: Python :: 3.8
